stupid_calc/__init__.py
stupid_calc/main.py
pypi_test_calc-0.0.4.dist-info/METADATA
pypi_test_calc-0.0.4.dist-info/WHEEL
pypi_test_calc-0.0.4.dist-info/top_level.txt
pypi_test_calc-0.0.4.dist-info/RECORD
