Metadata-Version: 2.4
Name: pypi-test-calc
Version: 0.0.4
Summary: Test calculator package
Home-page: https://github.com/yourusername/your_package
Author: Your Name
Author-email: your.email@example.com
Classifier: Programming Language :: Python :: 3
Classifier: Operating System :: OS Independent
Dynamic: author-email
Dynamic: home-page
